odoo/addons/delivery_package_number/README.rst
odoo/addons/delivery_package_number/__init__.py
odoo/addons/delivery_package_number/__manifest__.py
odoo/addons/delivery_package_number/data/paperformat_data.xml
odoo/addons/delivery_package_number/i18n/delivery_package_number.pot
odoo/addons/delivery_package_number/i18n/es.po
odoo/addons/delivery_package_number/i18n/it.po
odoo/addons/delivery_package_number/i18n/sl.po
odoo/addons/delivery_package_number/models/__init__.py
odoo/addons/delivery_package_number/models/stock_picking.py
odoo/addons/delivery_package_number/models/stock_picking_type.py
odoo/addons/delivery_package_number/readme/CONTRIBUTORS.md
odoo/addons/delivery_package_number/readme/DESCRIPTION.md
odoo/addons/delivery_package_number/readme/USAGE.md
odoo/addons/delivery_package_number/reports/report_package_number.xml
odoo/addons/delivery_package_number/security/ir.model.access.csv
odoo/addons/delivery_package_number/static/description/icon.png
odoo/addons/delivery_package_number/static/description/index.html
odoo/addons/delivery_package_number/tests/__init__.py
odoo/addons/delivery_package_number/tests/test_delivery_package_number.py
odoo/addons/delivery_package_number/views/stock_picking_type_views.xml
odoo/addons/delivery_package_number/views/stock_picking_views.xml
odoo/addons/delivery_package_number/wizard/__init__.py
odoo/addons/delivery_package_number/wizard/stock_backorder_confirmation.py
odoo/addons/delivery_package_number/wizard/stock_number_package_validate_wiz.py
odoo/addons/delivery_package_number/wizard/stock_number_package_validate_wiz_view.xml
odoo_addon_delivery_package_number-19.0.1.0.0.2.dist-info/METADATA
odoo_addon_delivery_package_number-19.0.1.0.0.2.dist-info/WHEEL
odoo_addon_delivery_package_number-19.0.1.0.0.2.dist-info/top_level.txt
odoo_addon_delivery_package_number-19.0.1.0.0.2.dist-info/RECORD
